{
    "name": "mini-v2",
    "version": "1.0.0",
    "description": "The calliope mini v2 core library",
    "compileServiceVariant": "minidal",
    "core": true,
    "dependencies": {
        "core": "file:../core",
        "core-mini-dal": "file:../core-mini-dal"
    },
    "files": [
        "README.md",
        "board.json"
    ],
    "yotta": {
        "config": {
            "microbit-dal": {
                "sram_end": "0x20008000",
                "RAM_SIZE": "\"32K\""
            }
        }
    }
}
